{
    "Rk": 71,
    "Player": "Dorian Finney-Smith",
    "Pos": "PF",
    "Age": 28,
    "Tm": "DAL",
    "G": 18,
    "GS": 18,
    "MP": 38.2,
    "FG": 4.1,
    "FGA": 8.7,
    "FGp": 0.471,
    "threeP": 2.6,
    "threePA": 6.0,
    "threePp": 0.426,
    "twoP": 1.6,
    "twoPA": 2.7,
    "twoPp": 0.571,
    "eFGp": 0.618,
    "FT": 0.9,
    "FTA": 1.3,
    "FTp": 0.708,
    "ORB": 1.8,
    "DRB": 3.7,
    "TRB": 5.5,
    "AST": 1.9,
    "STL": 0.9,
    "BLK": 0.4,
    "TOV": 1.0,
    "PF": 2.9,
    "PTS": 11.7
}