{
    "Rk": 6,
    "Player": "Jose Alvarado",
    "Pos": "PG",
    "Age": 23,
    "Tm": "NOP",
    "G": 6,
    "GS": 0,
    "MP": 19.5,
    "FG": 2.7,
    "FGA": 5.5,
    "FGp": 0.485,
    "threeP": 1.0,
    "threePA": 2.7,
    "threePp": 0.375,
    "twoP": 1.7,
    "twoPA": 2.8,
    "twoPp": 0.588,
    "eFGp": 0.576,
    "FT": 1.7,
    "FTA": 2.2,
    "FTp": 0.769,
    "ORB": 0.3,
    "DRB": 1.0,
    "TRB": 1.3,
    "AST": 1.5,
    "STL": 1.2,
    "BLK": 0.2,
    "TOV": 1.2,
    "PF": 3.0,
    "PTS": 8.0
}